{
    "version": "1.2.2",
    "description": "Kills Adobe's pesky background apps and more!",
    "homepage": "https://github.com/eaaasun/CCStopper",
    "license": "GPL-3.0",
    "url": "https://github.com/eaaasun/CCStopper/releases/download/v1.2.2/CCStopper.zip",
    "bin": "CCStopper.bat",
    "hash": "5a36a0928d4d31a3adaa65864e600d4f96dff9189d17bb89febec6e23f664cb7",
    "extract_dir": "CCStopper",
    "shortcuts": [
        [
            "CCStopper.bat",
            "CCStoper"
        ]
    ],
    "checkver": "github",
    "autoupdate": {
        "url": "https://github.com/eaaasun/CCStopper/releases/download/v$version/CCStopper.zip"
    }
}
